{
    "status": "OK",
    "copyright": "Copyright (c) 2025 The New York Times Company. All Rights Reserved.",
    "response": {
        "docs": [
            {
                "abstract": "Robert F. Kennedy Jr. is destroying the public trust.",
                "byline": {
                    "original": "By David Wallace-Wells"
                },
                "document_type": "article",
                "headline": {
                    "main": "‘I Think He Is About to Destroy Vaccines in This Country’",
                    "kicker": "David Wallace-Wells",
                    "print_headline": "‘I Think He Is About to Destroy Vaccines in This Country’"
                },
                "_id": "nyt://article/33a5fae5-cb05-51d6-9790-55f95234a8d8",
                "keywords": [
                    {
                        "name": "Subject",
                        "value": "Vaccination and Immunization",
                        "rank": 1
                    },
                    {
                        "name": "Subject",
                        "value": "United States Politics and Government",
                        "rank": 2
                    },
                    {
                        "name": "Person",
                        "value": "Kennedy, Robert F Jr",
                        "rank": 3
                    },
                    {
                        "name": "Subject",
                        "value": "Rumors and Misinformation",
                        "rank": 4
                    },
                    {
                        "name": "Person",
                        "value": "Malone, Robert (1959- )",
                        "rank": 5
                    },
                    {
                        "name": "Organization",
                        "value": "Health and Human Services Department",
                        "rank": 6
                    },
                    {
                        "name": "Organization",
                        "value": "Centers for Disease Control and Prevention",
                        "rank": 7
                    }
                ],
                "multimedia": {
                    "caption": "",
                    "credit": "Illustration by Ibrahim Rayintakath",
                    "default": {
                        "url": "https://static01.nyt.com/images/2025/06/29/magazine/29mag-climate/29mag-climate-articleLarge.jpg",
                        "height": 600,
                        "width": 600
                    },
                    "thumbnail": {
                        "url": "https://static01.nyt.com/images/2025/06/29/magazine/29mag-climate/29mag-climate-thumbStandard.jpg",
                        "height": 75,
                        "width": 75
                    }
                },
                "news_desk": "OpEd",
                "print_page": "18",
                "print_section": "MM",
                "pub_date": "2025-06-18T19:00:03Z",
                "section_name": "Opinion",
                "snippet": "Robert F. Kennedy Jr. is destroying the public trust.",
                "source": "The New York Times",
                "subsection_name": "",
                "type_of_material": "Op-Ed",
                "uri": "nyt://article/33a5fae5-cb05-51d6-9790-55f95234a8d8",
                "web_url": "https://www.nytimes.com/2025/06/18/opinion/kennedy-vaccine-panel.html",
                "word_count": 1548
            }
        ],
        "metadata": {
            "hits": 1,
            "offset": 0,
            "time": 97
        }
    }
}